embed/__init__.py
embed/embedd.py
embedd-0.1.dist-info/LICENSE
embedd-0.1.dist-info/METADATA
embedd-0.1.dist-info/WHEEL
embedd-0.1.dist-info/top_level.txt
embedd-0.1.dist-info/RECORD
