Metadata-Version: 2.1
Name: embedd
Version: 0.1
Summary: A simple example Python package
Author: prise
Author-email: 1165318929@qq.com
License-File: LICENSE
Requires-Dist: annotated-types >=0.6.0
Requires-Dist: anyio >=3.7.1
Requires-Dist: certifi >=2023.7.22
Requires-Dist: colorama >=0.4.6
Requires-Dist: distro >=1.8.0
Requires-Dist: fastapi >=0.104.1
Requires-Dist: h11 >=0.14.0
Requires-Dist: httpcore >=1.0.2
Requires-Dist: httpx >=0.25.1
Requires-Dist: idna >=3.4
Requires-Dist: numpy >=1.26.2
Requires-Dist: openai >=1.2.4
Requires-Dist: pandas >=2.1.3
Requires-Dist: pydantic >=2.5.1
Requires-Dist: pydantic-core >=2.14.3
Requires-Dist: python-dateutil >=2.8.2
Requires-Dist: pytz >=2023.3.post1
Requires-Dist: six >=1.16.0
Requires-Dist: sniffio >=1.3.0
Requires-Dist: starlette >=0.27.0
Requires-Dist: tqdm >=4.66.1
Requires-Dist: typing-extensions >=4.8.0
Requires-Dist: tzdata >=2023.3
